README.md
setup.py
memprofiler/__init__.py
memprofiler/memprofiler.py
memprofiler.egg-info/PKG-INFO
memprofiler.egg-info/SOURCES.txt
memprofiler.egg-info/dependency_links.txt
memprofiler.egg-info/requires.txt
memprofiler.egg-info/top_level.txt