Metadata-Version: 2.1
Name: memprofiler
Version: 0.1.2
Summary: A simple IPython extension for monitoring memory usage of Jupyter notebook cells.
Home-page: https://github.com/aleixalcacer/memprofiler
Author: Aleix Alcacer
Author-email: aleixalcacer@gmail.com
License: BSD (3-clause)
Platform: UNKNOWN
Classifier: Development Status :: 5 - Production/Stable
Classifier: Environment :: Console
Classifier: Intended Audience :: Developers
Classifier: License :: OSI Approved :: BSD License
Classifier: Natural Language :: English
Classifier: Operating System :: OS Independent
Classifier: Programming Language :: Python
Classifier: Topic :: Software Development :: Libraries :: Python Modules
Requires-Python: >=3.4
